listengb/__init__.py
listengb/core.py
listengb-0.1.0.dist-info/licenses/LICENSE
listengb-0.1.0.dist-info/METADATA
listengb-0.1.0.dist-info/WHEEL
listengb-0.1.0.dist-info/top_level.txt
listengb-0.1.0.dist-info/RECORD
