Metadata-Version: 2.4
Name: listengb
Version: 0.1.0
Summary: A UDP broadcast listener library for Python
Home-page: https://github.com/yourusername/listengb
Author: Your Name
Author-email: your.email@example.com
Keywords: udp,broadcast,listener,network
Classifier: Programming Language :: Python :: 3
Classifier: License :: OSI Approved :: MIT License
Classifier: Operating System :: OS Independent
Requires-Python: >=3.6
License-File: LICENSE
Dynamic: author
Dynamic: author-email
Dynamic: classifier
Dynamic: description
Dynamic: description-content-type
Dynamic: home-page
Dynamic: keywords
Dynamic: license-file
Dynamic: requires-python
Dynamic: summary
